pymyenv/__init__.py
pymyenv/common.py
pymyenv/main.py
pymyenv/static.py
pymyenv-0.0.8.dist-info/LICENSE
pymyenv-0.0.8.dist-info/METADATA
pymyenv-0.0.8.dist-info/WHEEL
pymyenv-0.0.8.dist-info/entry_points.txt
pymyenv-0.0.8.dist-info/top_level.txt
pymyenv-0.0.8.dist-info/RECORD
